dbbasic_sessions/__init__.py
dbbasic_sessions-3.0.0.dist-info/licenses/LICENSE
tests/__init__.py
tests/test_performance.py
tests/test_security.py
tests/test_unit.py
dbbasic_sessions-3.0.0.dist-info/METADATA
dbbasic_sessions-3.0.0.dist-info/WHEEL
dbbasic_sessions-3.0.0.dist-info/top_level.txt
dbbasic_sessions-3.0.0.dist-info/RECORD
